{"2009-10": {"GP": 73, "FGM": 230, "FGA": 520, "FG3M": 62, "FG3A": 159, "FTM": 65, "FTA": 86, "REB": 191, "AST": 280, "STL": 79, "BLK": 18, "TOV": 156, "PTS": 587}, "2010-11": {"GP": 82, "FGM": 446, "FGA": 999, "FG3M": 81, "FG3A": 222, "FTM": 172, "FTA": 209, "REB": 332, "AST": 531, "STL": 120, "BLK": 29, "TOV": 218, "PTS": 1145}, "2011-12": {"GP": 65, "FGM": 360, "FGA": 834, "FG3M": 65, "FG3A": 171, "FTM": 94, "FTA": 120, "REB": 212, "AST": 290, "STL": 103, "BLK": 18, "TOV": 135, "PTS": 879}, "2012-13": {"GP": 78, "FGM": 555, "FGA": 1288, "FG3M": 91, "FG3A": 247, "FTM": 182, "FTA": 242, "REB": 329, "AST": 625, "STL": 123, "BLK": 32, "TOV": 292, "PTS": 1383}, "2013-14": {"GP": 34, "FGM": 203, "FGA": 454, "FG3M": 30, "FG3A": 77, "FTM": 51, "FTA": 63, "REB": 142, "AST": 268, "STL": 56, "BLK": 12, "TOV": 105, "PTS": 487}, "2014-15": {"GP": 40, "FGM": 238, "FGA": 534, "FG3M": 51, "FG3A": 135, "FTM": 65, "FTA": 76, "REB": 135, "AST": 274, "STL": 63, "BLK": 23, "TOV": 91, "PTS": 592}, "2015-16": {"GP": 65, "FGM": 410, "FGA": 935, "FG3M": 87, "FG3A": 259, "FTM": 182, "FTA": 216, "REB": 195, "AST": 391, "STL": 88, "BLK": 22, "TOV": 167, "PTS": 1089}, "2016-17": {"GP": 67, "FGM": 405, "FGA": 893, "FG3M": 100, "FG3A": 281, "FTM": 119, "FTA": 168, "REB": 264, "AST": 488, "STL": 100, "BLK": 44, "TOV": 194, "PTS": 1029}, "2017-18": {"GP": 81, "FGM": 615, "FGA": 1244, "FG3M": 120, "FG3A": 356, "FTM": 187, "FTA": 238, "REB": 365, "AST": 486, "STL": 123, "BLK": 64, "TOV": 213, "PTS": 1537}, "2018-19": {"GP": 67, "FGM": 547, "FGA": 1159, "FG3M": 118, "FG3A": 363, "FTM": 208, "FTA": 271, "REB": 334, "AST": 518, "STL": 109, "BLK": 54, "TOV": 210, "PTS": 1420}, "2019-20": {"GP": 61, "FGM": 458, "FGA": 1006, "FG3M": 122, "FG3A": 346, "FTM": 129, "FTA": 182, "REB": 293, "AST": 408, "STL": 99, "BLK": 48, "TOV": 184, "PTS": 1167}, "2020-21": {"GP": 59, "FGM": 414, "FGA": 823, "FG3M": 111, "FG3A": 283, "FTM": 107, "FTA": 136, "REB": 268, "AST": 357, "STL": 96, "BLK": 37, "TOV": 127, "PTS": 1046}, "2021-22": {"GP": 67, "FGM": 478, "FGA": 954, "FG3M": 132, "FG3A": 321, "FTM": 137, "FTA": 180, "REB": 301, "AST": 457, "STL": 108, "BLK": 29, "TOV": 183, "PTS": 1225}, "2022-23": {"GP": 16, "FGM": 109, "FGA": 248, "FG3M": 31, "FG3A": 95, "FTM": 35, "FTA": 40, "REB": 79, "AST": 116, "STL": 26, "BLK": 9, "TOV": 51, "PTS": 284}}